pandas_weighting/__init__.py
pandas_weighting/func.py
pandas_weighting-0.0.2.dist-info/LICENSE
pandas_weighting-0.0.2.dist-info/METADATA
pandas_weighting-0.0.2.dist-info/WHEEL
pandas_weighting-0.0.2.dist-info/top_level.txt
pandas_weighting-0.0.2.dist-info/RECORD
