Metadata-Version: 2.1
Name: pandas-weighting
Version: 0.0.2
Summary: General level weighting of Pandas Dataframes
Home-page: https://github.com/JaakkoRoponen/pandas-weighting
Author: Jaakko Roponen
License: UNKNOWN
Platform: UNKNOWN
Classifier: Programming Language :: Python :: 3
Classifier: License :: OSI Approved :: MIT License
Classifier: Operating System :: OS Independent
Requires-Python: >=3.6
Requires-Dist: pandas
